d8/__init__.py
d8/main.py
d8/core/__init__.py
d8/core/base_dataset.py
d8/core/downloader.py
d8/core/reader.py
d8/image_classification/__init__.py
d8/image_classification/constructing.py
d8/image_classification/dataset.py
d8/object_detection/__init__.py
d8/object_detection/constructing.py
d8/object_detection/dataset.py
d8/tabular_classification/__init__.py
d8/tabular_classification/constructing.py
d8/tabular_classification/dataset.py
d8-0.0.2.post0.dist-info/LICENSE
d8-0.0.2.post0.dist-info/METADATA
d8-0.0.2.post0.dist-info/WHEEL
d8-0.0.2.post0.dist-info/entry_points.txt
d8-0.0.2.post0.dist-info/top_level.txt
d8-0.0.2.post0.dist-info/zip-safe
d8-0.0.2.post0.dist-info/RECORD
